MANIFEST.in
README.rst
setup.cfg
setup.py
crosscompute_video/__init__.py
crosscompute_video/type.jinja2
crosscompute_video.egg-info/PKG-INFO
crosscompute_video.egg-info/SOURCES.txt
crosscompute_video.egg-info/dependency_links.txt
crosscompute_video.egg-info/entry_points.txt
crosscompute_video.egg-info/not-zip-safe
crosscompute_video.egg-info/requires.txt
crosscompute_video.egg-info/top_level.txt