Metadata-Version: 1.1
Name: crosscompute-video
Version: 0.7.5
Summary: Video data type plugin for CrossCompute
Home-page: https://github.com/salah93/crosscompute-video
Author: Salah Ahmed
Author-email: salah93@crosscompute.com
License: UNKNOWN
Keywords: web crosscompute
Platform: UNKNOWN
Classifier: Programming Language :: Python
Classifier: Framework :: Pyramid
Classifier: Topic :: Internet :: WWW/HTTP :: WSGI :: Application
Classifier: License :: OSI Approved :: MIT License
